setup.py
fkjghdkjghlDhbsli86432/__init__.py
fkjghdkjghlDhbsli86432/one.py
fkjghdkjghlDhbsli86432/two.py
fkjghdkjghlDhbsli86432.egg-info/PKG-INFO
fkjghdkjghlDhbsli86432.egg-info/SOURCES.txt
fkjghdkjghlDhbsli86432.egg-info/dependency_links.txt
fkjghdkjghlDhbsli86432.egg-info/top_level.txt