Metadata-Version: 2.1
Name: fkjghdkjghlDhbsli86432
Version: 0.0.1
Summary: My Package
Author: Dasha
Author-email: d_knishenko@mail.ru
